{
  "policy_version": "0.8.2",
  "status": "CANONICAL_CLASSIFICATION_ENGINE_READY_SOURCE_SNAPSHOT_REQUIRED",
  "universe_id": "ARM-EUROSTAT-HICP-ARMILAR-V1-PILOT-V0.8.2",
  "reference_period": "2021-01",
  "categories": [
    "ARM01",
    "ARM02",
    "ARM03",
    "ARM04",
    "ARM05",
    "ARM06",
    "ARM07",
    "ARM08",
    "ARM09"
  ],
  "allowed_sources": [
    "EUROSTAT"
  ],
  "required_price_evidence_class": "P1_OFFICIAL_CATEGORY",
  "minimum_complete_months": 2,
  "normalization_rule": "FIXED_UNIVERSE_NORMALISE_ONCE",
  "aggregation_mode": "PPP_WEIGHTED_LOCAL_PRICE_RELATIVES",
  "fx_treatment": "NOT_INCLUDED",
  "universe_fixed": true,
  "silent_monthly_renormalisation_allowed": false,
  "future_observation_use_allowed": false,
  "experimental": true,
  "research_release_allowed": false,
  "monetary_release_allowed": false,
  "classification_id": "ARMILAR_CONSUMPTION_CLASSIFICATION",
  "classification_version": "1.0.0",
  "classification_file": "config/armilar_consumption_classification_v1.json",
  "mapping_file": "config/classification_mappings/ecoicop_v1_to_armilar_v1.csv",
  "provisional_next_mapping_file": "config/classification_mappings/ecoicop_v2_to_armilar_v1_provisional.csv",
  "source_categories": [
    "CP01",
    "CP02",
    "CP03",
    "CP04",
    "CP05",
    "CP06",
    "CP07",
    "CP08",
    "CP09",
    "CP10",
    "CP11",
    "CP12"
  ],
  "raw_source_detail_preserved": true,
  "canonical_aggregation_changes_total_index": false,
  "price_concept": "HICP_HOUSEHOLD_FINAL_MONETARY_CONSUMPTION",
  "weight_concept": "ARMILAR_HFCE_PPP_2021",
  "concept_alignment_status": "PARTIAL_HFMCE_HFCE_SCOPE_MISMATCH",
  "ecoicop_v2_bridge_status": "BACKSERIES_VALIDATION_REQUIRED"
}
